NeuNorm/__init__.py
NeuNorm/_utilities.py
NeuNorm/_version.py
NeuNorm/exporter.py
NeuNorm/loader.py
NeuNorm/normalization.py
NeuNorm/roi.py
neunorm-1.6.12.dist-info/LICENSE
neunorm-1.6.12.dist-info/METADATA
neunorm-1.6.12.dist-info/WHEEL
neunorm-1.6.12.dist-info/top_level.txt
neunorm-1.6.12.dist-info/RECORD
